[
  {
    "FORMAT": "7 reels ",
    "COMMENTS": " ",
    "DATES": "1948-1970 ",
    "PUBLISHER": "American Communication Association",
    "MF_ID": 1,
    "TITLE": "ACA News"
  },
  {
    "FORMAT": "1 reel ",
    "COMMENTS": " ",
    "DATES": "Aug. 1885 - May 1889 ",
    "PUBLISHER": "Knights of Labor, District Assembly 50, Detroit",
    "MF_ID": 2,
    "TITLE": "Advance and the Labor Leaf"
  },
  {
    "FORMAT": "8 reels ",
    "COMMENTS": "AFL-CIO Milwaukee Labor Press 9 reels, 1959-April 1974 ",
    "DATES": "Aug. 1942 - 1958 ",
    "PUBLISHER": "Milwaukee Federated Trades Council",
    "MF_ID": 3,
    "TITLE": "AFL Milwaukee Labor Press"
  },
  {
    "FORMAT": "1 reel ",
    "COMMENTS": " ",
    "DATES": "1934 - 1935 ",
    "PUBLISHER": "Trade Union Committee for Unemployment Insurance and Relief, New York",
    "MF_ID": 4,
    "TITLE": "AFL Rank and File Federationist"
  },
  {
    "FORMAT": "1 reel ",
    "COMMENTS": " ",
    "DATES": "Oct. 1884 - Feb. 1889 ",
    "PUBLISHER": "Working Peoples International Association",
    "MF_ID": 5,
    "TITLE": "Alarm"
  },
  {
    "FORMAT": "1 reel ",
    "COMMENTS": " ",
    "DATES": "July 1943 - May 1944 ",
    "PUBLISHER": "Aluminum Workers of America",
    "MF_ID": 6,
    "TITLE": "Aluminum Workers News Digest"
  },
  {
    "FORMAT": "1 reel ",
    "COMMENTS": " ",
    "DATES": "Dec. 1896 - Nov. 1901 ",
    "PUBLISHER": "Amalgamated Sheet Metal Workers' International Association",
    "MF_ID": 7,
    "TITLE": "Amalgamated Sheet Metal Workers' Journal"
  },
  {
    "FORMAT": "1 reel ",
    "COMMENTS": " ",
    "DATES": "Nov. 1902 - Dec. 1904 ",
    "PUBLISHER": "American Labor Union",
    "MF_ID": 8,
    "TITLE": "American Labor Union Journal"
  },
  {
    "FORMAT": "1 reel ",
    "COMMENTS": " ",
    "DATES": "Jan. - Aug. 1940 ",
    "PUBLISHER": "Kommunistiske Internasjonale, Oslo, Norway",
    "MF_ID": 9,
    "TITLE": "Arbeideren"
  },
  {
    "FORMAT": "1 reel ",
    "COMMENTS": " ",
    "DATES": "June 1945 - Jan. 1952 ",
    "PUBLISHER": "Associated Unions of America",
    "MF_ID": 10,
    "TITLE": "AUA Report"
  },
  {
    "FORMAT": "1 reel ",
    "COMMENTS": " ",
    "DATES": "Mar. 1921 - July 1921 ",
    "PUBLISHER": "International Typographical Union. Local No. 232, Binghamton, New York",
    "MF_ID": 11,
    "TITLE": "Binghamton Advocate"
  },
  {
    "FORMAT": "3 reels ",
    "COMMENTS": " ",
    "DATES": "Nov. 1929 - Mar. 1968 ",
    "PUBLISHER": "Brotherhood of Sleeping Car Porters",
    "MF_ID": 12,
    "TITLE": "Black Worker"
  },
  {
    "FORMAT": "2 reels ",
    "COMMENTS": " ",
    "DATES": "1898 - 1909 ",
    "PUBLISHER": "Labor Education League, England",
    "MF_ID": 13,
    "TITLE": "Blackburn Labour Journal (Workers Tribune)"
  },
  {
    "FORMAT": "1 reel ",
    "COMMENTS": " ",
    "DATES": "1952 - 1959 ",
    "PUBLISHER": "Seafarer's International Union of North America, Brotherhood of Marine Engineers",
    "MF_ID": 14,
    "TITLE": "BME Marine Engineer"
  },
  {
    "FORMAT": "1 reel ",
    "COMMENTS": " ",
    "DATES": "1903-1908 ",
    "PUBLISHER": "Home, Washington ",
    "MF_ID": 31,
    "TITLE": "Demonstrator"
  },
  {
    "FORMAT": "1 reel ",
    "COMMENTS": " ",
    "DATES": "July 1917 - Nov 1917 ",
    "PUBLISHER": "Metal Mine Workers Union of Butte and Anaconda",
    "MF_ID": 16,
    "TITLE": "Butte & Anaconda Joint Strike Bulletin"
  },
  {
    "FORMAT": "1 reel ",
    "COMMENTS": "STACKS: HD 6515 H82 N53, 1946-1959, 1969-1974 ",
    "DATES": "Apr. 1959 - Sept./Oct. 1968 ",
    "PUBLISHER": "Hotel and Restaurant Employees and Bartenders International Union. \r\n Cafeteria Employees Union, Local 302, New York, NY \r\n",
    "MF_ID": 17,
    "TITLE": "Cafeteria Call "
  },
  {
    "FORMAT": "11 reels ",
    "COMMENTS": "Contents listed on reels ",
    "DATES": " ",
    "PUBLISHER": "",
    "MF_ID": 18,
    "TITLE": "Canadian Labor Newspapers "
  },
  {
    "FORMAT": "1 reel ",
    "COMMENTS": "(formerly New Democracy) ",
    "DATES": "Aug. 1923 - Nov. 1931 ",
    "PUBLISHER": "",
    "MF_ID": 19,
    "TITLE": "Canadian Labour World "
  },
  {
    "FORMAT": "3 reels ",
    "COMMENTS": " ",
    "DATES": "Mar. 1915 - Mar. 1953 ",
    "PUBLISHER": "Canadian Brotherhood of Railroad Employees and Other Transport Workers ",
    "MF_ID": 20,
    "TITLE": "Canadian Railroad Employees' Monthly "
  },
  {
    "FORMAT": "1 reel ",
    "COMMENTS": " ",
    "DATES": "Jan. 1899 - May 1908 ",
    "PUBLISHER": "Carriage and Wagon Workers' International Union of North America ",
    "MF_ID": 21,
    "TITLE": "Carriage and Wagon Workers' Journal "
  },
  {
    "FORMAT": "1 reel ",
    "COMMENTS": "STACKS: HD 6521 A1 C15, 1956-1958 ",
    "DATES": "Apr. 1956 - July/Aug. 1958 ",
    "PUBLISHER": "Canadian Congress of Labour ",
    "MF_ID": 22,
    "TITLE": "CCL News "
  },
  {
    "FORMAT": "1 reel ",
    "COMMENTS": " ",
    "DATES": "Oct. 1951- May 1954 ",
    "PUBLISHER": "Congress of Industrial Organizations ",
    "MF_ID": 23,
    "TITLE": "CIO World Affairs Bulletin "
  },
  {
    "FORMAT": "1 reel ",
    "COMMENTS": " ",
    "DATES": "Nov. 1946 - Spet. 1947 ",
    "PUBLISHER": "International Union, United Automobile, Aircraft and Agricultural Implement Workers of America. \r\nCompetitive Shop Dept. \r\n",
    "MF_ID": 24,
    "TITLE": "Competitive Shop Organizer "
  },
  {
    "FORMAT": "1 reel ",
    "COMMENTS": " ",
    "DATES": "1942 - 1944 ",
    "PUBLISHER": "Canadian Congress of Labour, Pacific Coast ",
    "MF_ID": 25,
    "TITLE": "Congress News "
  },
  {
    "FORMAT": "1 reel ",
    "COMMENTS": " ",
    "DATES": "1946-1949 ",
    "PUBLISHER": "Consolidation Committee of Engineers, Cleveland, Ohio ",
    "MF_ID": 26,
    "TITLE": "Consolidator"
  },
  {
    "FORMAT": "1 reel ",
    "COMMENTS": " ",
    "DATES": "Feb. 1953 - Jan. 1954 ",
    "PUBLISHER": "International Brotherhood of Teamsters, Chauffers, Warehousemen and Helpers of America. \r\nTeamsters Bay Arear Warehouse Council \r\n",
    "MF_ID": 27,
    "TITLE": "Council News"
  },
  {
    "FORMAT": "1 reel ",
    "COMMENTS": " ",
    "DATES": "Nov. 1917 - Nov. 1918 ",
    "PUBLISHER": "Industrial Workers of the World. General Defense Committee ",
    "MF_ID": 28,
    "TITLE": "Defense News Bulletin "
  },
  {
    "FORMAT": "1 reel ",
    "COMMENTS": " ",
    "DATES": "Jan. 1942-July 1947 ",
    "PUBLISHER": "Distillery, Rectifying and Wine Workers' International Union of America ",
    "MF_ID": 32,
    "TITLE": "Distillery, Rectifying & Wine Workers Journal "
  },
  {
    "FORMAT": "1 reel ",
    "COMMENTS": " ",
    "DATES": "1894-1896 ",
    "PUBLISHER": "National Free Labour Association ",
    "MF_ID": 33,
    "TITLE": "Extracts from the Free Labour Gazette "
  },
  {
    "FORMAT": "1 reel ",
    "COMMENTS": " ",
    "DATES": "Jan. 1930-Dec. 1934 ",
    "PUBLISHER": "Farmer-Labor Association, St. Paul, MN ",
    "MF_ID": 34,
    "TITLE": "Free-Labor Leader "
  },
  {
    "FORMAT": "2 reels ",
    "COMMENTS": " ",
    "DATES": "Mar. 1943-1949 ",
    "PUBLISHER": "United Farm Equipment and Metal Workers of America ",
    "MF_ID": 35,
    "TITLE": "FE News "
  },
  {
    "FORMAT": "1 reel ",
    "COMMENTS": " ",
    "DATES": "Feb. 1939-May 1946 ",
    "PUBLISHER": "United Federal Workers of America ",
    "MF_ID": 36,
    "TITLE": "Federal Record "
  },
  {
    "FORMAT": "1 reel ",
    "COMMENTS": " ",
    "DATES": "1863-1866 ",
    "PUBLISHER": "Jonathan C. Fincher, Philadelphia ",
    "MF_ID": 37,
    "TITLE": "Fincher's Trades' Review "
  },
  {
    "FORMAT": "1 reel ",
    "COMMENTS": " ",
    "DATES": "Nov. 1894-Apr. 1896 ",
    "PUBLISHER": "National Free Labour Association ",
    "MF_ID": 38,
    "TITLE": "Free Labour Gazette "
  },
  {
    "FORMAT": "2 reels ",
    "COMMENTS": " ",
    "DATES": "Jan. 1899-Apr. 1896 ",
    "PUBLISHER": "National Free Labour Association ",
    "MF_ID": 39,
    "TITLE": "Free Labour Press "
  },
  {
    "FORMAT": "1 reel ",
    "COMMENTS": " ",
    "DATES": "June 1928-Apr. 1935 ",
    "PUBLISHER": "Amalgamated Food Workers of America ",
    "MF_ID": 40,
    "TITLE": "Free Voice of the... "
  },
  {
    "FORMAT": "1 reel ",
    "COMMENTS": " ",
    "DATES": "May 1961-May 1965 ",
    "PUBLISHER": "United Steelworkers of America. Great Lakes Seamen ",
    "MF_ID": 41,
    "TITLE": "Great Lakes Sailor "
  },
  {
    "FORMAT": " ",
    "COMMENTS": "See Kheel Center, Ives 144 ",
    "DATES": "1913-1919 ",
    "PUBLISHER": "League for Industrial Democracy, New York ",
    "MF_ID": 42,
    "TITLE": "Intercollegiate Socialist "
  },
  {
    "FORMAT": "1 reel ",
    "COMMENTS": " ",
    "DATES": "Aug. 1941-Dec. 1948 ",
    "PUBLISHER": "International Fisherman and Allied Workers of America ",
    "MF_ID": 43,
    "TITLE": "International Fisherman and Allied Worker "
  },
  {
    "FORMAT": "1 reel ",
    "COMMENTS": " ",
    "DATES": "Feb.-Dec. 1927 ",
    "PUBLISHER": "Labour and Socialist International ",
    "MF_ID": 44,
    "TITLE": "International Information "
  },
  {
    "FORMAT": "5 reels ",
    "COMMENTS": " ",
    "DATES": "Feb. 1942-July 1971 ",
    "PUBLISHER": "Laundry Workers' International Union ",
    "MF_ID": 45,
    "TITLE": "International Laundry Worker "
  },
  {
    "FORMAT": "2 reels ",
    "COMMENTS": " ",
    "DATES": "July 1925-Dec. 1935, Dec. 1937-Apr. 1938 ",
    "PUBLISHER": "International Association of Oil Field, Gaswell and Refinery Workers of America. \r\nLong Beach, CA and Washington, DC \r\n",
    "MF_ID": 46,
    "TITLE": "International Oil Worker "
  },
  {
    "FORMAT": "2 reels ",
    "COMMENTS": " ",
    "DATES": "1900-1953 ",
    "PUBLISHER": "International Wood Carvers Association of North America ",
    "MF_ID": 47,
    "TITLE": "International Woodcarver "
  },
  {
    "FORMAT": "3 reels ",
    "COMMENTS": " ",
    "DATES": "1883-1887 ",
    "PUBLISHER": "",
    "MF_ID": 48,
    "TITLE": "John Swinton's Paper "
  },
  {
    "FORMAT": " ",
    "COMMENTS": "see Kheel Center, Room 144 ",
    "DATES": " ",
    "PUBLISHER": "Knights of Labor ",
    "MF_ID": 49,
    "TITLE": "Journal of the Knights of Labor "
  },
  {
    "FORMAT": " ",
    "COMMENTS": "see Kheel Center, Room 144 ",
    "DATES": " ",
    "PUBLISHER": "Knights of Labor ",
    "MF_ID": 50,
    "TITLE": "Journal of United Labor "
  },
  {
    "FORMAT": "3 reels ",
    "COMMENTS": "(Weekly Compendium) ",
    "DATES": "Nov. 1897-Apr. 1911 ",
    "PUBLISHER": "International Building Trades Council of America ",
    "MF_ID": 51,
    "TITLE": "Labor Compendium "
  },
  {
    "FORMAT": "1 reel ",
    "COMMENTS": "(English edition of Le Travail) ",
    "DATES": "Feb. 1966-Jan. 1969 ",
    "PUBLISHER": "Confederation des Syndicats National, Canada ",
    "MF_ID": 52,
    "TITLE": "Labour "
  },
  {
    "FORMAT": "1 reel ",
    "COMMENTS": " ",
    "DATES": "Nov. 1939-Feb. 1940 ",
    "PUBLISHER": "Hotel and Restaurant Employees and Bartenders International Union. \r\nHotel and Club Employees Union, Local 6, New York \r\n",
    "MF_ID": 53,
    "TITLE": "Local 6 News "
  },
  {
    "FORMAT": "1 reel ",
    "COMMENTS": " ",
    "DATES": "July 1916-Oct. 1918 ",
    "PUBLISHER": "Brotherhood of Maintenence of Way Employees of Greensboro, NC ",
    "MF_ID": 54,
    "TITLE": "Maintenence of Way Guide "
  },
  {
    "FORMAT": " ",
    "COMMENTS": "see Kheel Center, Room 144 ",
    "DATES": "1834-1835 ",
    "PUBLISHER": "",
    "MF_ID": 55,
    "TITLE": "The Man "
  },
  {
    "FORMAT": " ",
    "COMMENTS": "see Kheel Center, Room 144 ",
    "DATES": "1828-1834 ",
    "PUBLISHER": "",
    "MF_ID": 56,
    "TITLE": "Mechanics Free Press "
  },
  {
    "FORMAT": "2 reels ",
    "COMMENTS": "(incomplete) ",
    "DATES": "Nov. 1917-May/June 1928 ",
    "PUBLISHER": "Brotherhood of Sleeping Car Porters ",
    "MF_ID": 57,
    "TITLE": "Messenger"
  },
  {
    "FORMAT": " ",
    "COMMENTS": "see Kheel Center, Room 144 ",
    "DATES": "1836-1837 ",
    "PUBLISHER": "Workingmen's National Society for the Diffusion of useful Knowledge ",
    "MF_ID": 58,
    "TITLE": "National Laborer "
  },
  {
    "FORMAT": "4 reels ",
    "COMMENTS": " ",
    "DATES": "1948-1969 ",
    "PUBLISHER": "National Council of Canadian Labour ",
    "MF_ID": 59,
    "TITLE": "National Labour Journal "
  },
  {
    "FORMAT": " ",
    "COMMENTS": "see Kheel Center, Room 144 ",
    "DATES": "1834-1836 ",
    "PUBLISHER": "New York City General Trades Union ",
    "MF_ID": 60,
    "TITLE": "National Trades Union "
  },
  {
    "FORMAT": "1 reel ",
    "COMMENTS": "(incomplete) ",
    "DATES": 1834,
    "PUBLISHER": "Providence, RI ",
    "MF_ID": 61,
    "TITLE": "New England Artisan "
  },
  {
    "FORMAT": "4 reels ",
    "COMMENTS": " ",
    "DATES": "1865-1866 ",
    "PUBLISHER": "Editor, Benjamin Wood ",
    "MF_ID": 62,
    "TITLE": "New York Daily News "
  },
  {
    "FORMAT": "1 reel ",
    "COMMENTS": " ",
    "DATES": "June 1940-Apr. 1941 ",
    "PUBLISHER": "Transport Workers Union of America. Local 100, New York ",
    "MF_ID": 63,
    "TITLE": "New York Weekly Transport Bulletin "
  },
  {
    "FORMAT": "1 reel ",
    "COMMENTS": " ",
    "DATES": "Feb. 1948-Apr. 1956 ",
    "PUBLISHER": "Congres Canadien du Travail (Montreal) ",
    "MF_ID": 64,
    "TITLE": "Nouvelles Ouvrieres "
  },
  {
    "FORMAT": "2 reels ",
    "COMMENTS": " ",
    "DATES": "jan. 1935-Spet. 1948 ",
    "PUBLISHER": "United Office and Professional Workers of America ",
    "MF_ID": 65,
    "TITLE": "Office and Professional News "
  },
  {
    "FORMAT": "1 reel ",
    "COMMENTS": " ",
    "DATES": "Nov. 1928-Dec. 1955 ",
    "PUBLISHER": "Office Workers Union",
    "MF_ID": 66,
    "TITLE": "The Office Worker"
  },
  {
    "FORMAT": "1 reel ",
    "COMMENTS": " ",
    "DATES": "Apr. 1956-Nov. 1959 ",
    "PUBLISHER": "United States. Office of International Labor Affairs ",
    "MF_ID": 67,
    "TITLE": "OILA Memorandum "
  },
  {
    "FORMAT": "2 reels ",
    "COMMENTS": "(Far Eastern Monthly) ",
    "DATES": "1927-1932 ",
    "PUBLISHER": "Pan Pacific Trade Union Secretariat ",
    "MF_ID": 68,
    "TITLE": "Pan Pacific Worker "
  },
  {
    "FORMAT": "1 reel ",
    "COMMENTS": " ",
    "DATES": "Oct. 1912-June 1913 ",
    "PUBLISHER": "Pittsburgh Socialist Education League ",
    "MF_ID": 69,
    "TITLE": "Pittsburgh Socialist "
  },
  {
    "FORMAT": "4 reels ",
    "COMMENTS": "STACKS: HD 6500 S6 Q3, 1927-1929, 1935-1938 ",
    "DATES": "Sept. 1912-Feb. 1938 ",
    "PUBLISHER": "Quarry Workers' International Union of North America, Barre, VT ",
    "MF_ID": 70,
    "TITLE": "Quarry Workers' Journal "
  },
  {
    "FORMAT": "1 reel ",
    "COMMENTS": " ",
    "DATES": "Dec. 1953-Aug. 1954 ",
    "PUBLISHER": "U.D.F. Railroad workers of America United",
    "MF_ID": 71,
    "TITLE": "Railroad News, CIO"
  },
  {
    "FORMAT": "1 reel ",
    "COMMENTS": " ",
    "DATES": "May 1934-Apr. 1938 ",
    "PUBLISHER": "Sheboygan Central Labor Council, Sheboygan WI ",
    "MF_ID": 72,
    "TITLE": "Sheboygan Times "
  },
  {
    "FORMAT": " ",
    "COMMENTS": "see Kheel Center, Ives 144 ",
    "DATES": "1919-1921 ",
    "PUBLISHER": "",
    "MF_ID": 73,
    "TITLE": "Socialist Review "
  },
  {
    "FORMAT": "2 reels ",
    "COMMENTS": " ",
    "DATES": "Nov. 1940-May 1948 ",
    "PUBLISHER": "Textile Workers of America, Federation of Dyers, Finishers, Printers and Bleachers of America ",
    "MF_ID": 74,
    "TITLE": "Textile Dyer "
  },
  {
    "FORMAT": "5 reels ",
    "COMMENTS": " ",
    "DATES": "Jan. 1939-June 1954 ",
    "PUBLISHER": "Toledo, OH Central Labor Union ",
    "MF_ID": 75,
    "TITLE": "Toledo Union Leader "
  },
  {
    "FORMAT": "1 reel ",
    "COMMENTS": " ",
    "DATES": "1922-1934 ",
    "PUBLISHER": "Trade Union Educational League and Trade Union Unity League ",
    "MF_ID": 76,
    "TITLE": "Trade Union Unity League Newspapers "
  },
  {
    "FORMAT": "1 reel ",
    "COMMENTS": "Labor Unity - 1934 \r\nFord Workers - 1926-1927 \r\nWorkers News - Aug. 1926-Aug. 1927 \r\nWorkers Bulletin - Aug. 1926 \r\nFisher Body Worker - Oct. 1926-Aug. 1927 \r\n ",
    "DATES": "1922-1934 ",
    "PUBLISHER": "Auto Workers News",
    "MF_ID": 77,
    "TITLE": "Trade Union Unity League Publications "
  },
  {
    "FORMAT": "1 reel ",
    "COMMENTS": "(People's Press) \r\n(Work) \r\n ",
    "DATES": "March 1938-Nov. 1940 ",
    "PUBLISHER": "Workers Alliance of America ",
    "MF_ID": 86,
    "TITLE": "Workers Alliance "
  },
  {
    "FORMAT": "1 reel ",
    "COMMENTS": " ",
    "DATES": "May 1947-Nov. 1948 ",
    "PUBLISHER": "Transport Workers Union of America. Local 100, NY ",
    "MF_ID": 78,
    "TITLE": "Transport Voice "
  },
  {
    "FORMAT": "5 reels ",
    "COMMENTS": "(Kohlerian) ",
    "DATES": "Sept. 1943-May 1958 ",
    "PUBLISHER": "Kohler Workers Association, WI",
    "MF_ID": 79,
    "TITLE": "UAW Local 833 Reporter "
  },
  {
    "FORMAT": "1 reel ",
    "COMMENTS": " ",
    "DATES": "Aug. 1940-Apr. 1948 ",
    "PUBLISHER": "United Construction Workers ",
    "MF_ID": 80,
    "TITLE": "UCW News "
  },
  {
    "FORMAT": "1 reel ",
    "COMMENTS": " ",
    "DATES": "Apr. 1836-Jul. 1836 ",
    "PUBLISHER": "General Trades Union of Albany, Troy, Newark and New York ",
    "MF_ID": 81,
    "TITLE": "The Union "
  },
  {
    "FORMAT": "1 reel ",
    "COMMENTS": " ",
    "DATES": "Jan. 1936-Feb. 1950 ",
    "PUBLISHER": "Committee for Industrial Organization ",
    "MF_ID": 82,
    "TITLE": "Union News Service "
  },
  {
    "FORMAT": "1 reel ",
    "COMMENTS": " ",
    "DATES": "Aug. 1941-Jan. 1951 ",
    "PUBLISHER": "Retail Clerks International Association. Local 770, Los Angeles ",
    "MF_ID": 83,
    "TITLE": "Voice of 770 "
  },
  {
    "FORMAT": "5 reels ",
    "COMMENTS": " ",
    "DATES": "1911-1951 ",
    "PUBLISHER": "AFL",
    "MF_ID": 84,
    "TITLE": "Weekly News Service "
  },
  {
    "FORMAT": "1 reel ",
    "COMMENTS": " ",
    "DATES": "Aug. 1867-May 1868 ",
    "PUBLISHER": "Jonathon C. Fincher ",
    "MF_ID": 85,
    "TITLE": "Welcome Workman "
  },
  {
    "FORMAT": "1 reel ",
    "COMMENTS": " ",
    "DATES": "1920-1922 ",
    "PUBLISHER": "United Mine Workers of America. District 14, Pittsburg, KS ",
    "MF_ID": 87,
    "TITLE": "Workers' Chronicle "
  },
  {
    "FORMAT": "1 reel ",
    "COMMENTS": " ",
    "DATES": "1931-1932 ",
    "PUBLISHER": "Industrial Workers of the World. General Defense Committee ",
    "MF_ID": 88,
    "TITLE": "Workers Defense "
  },
  {
    "FORMAT": "9 reels ",
    "COMMENTS": " ",
    "DATES": "1901-Apr. 1913 ",
    "PUBLISHER": "Yorkshire Factory Times Office ",
    "MF_ID": 89,
    "TITLE": "Yorkshire Factory Times "
  }
]
